<record
	name="messageSet"
	type="minor">

	<fields>

		<!-- id -->

		<generated-id-field/>

		<!-- identity -->

		<parent-type-field
			column="parent_object_type_id"/>

		<parent-id-field
			column="parent_object_id"/>

		<code-field/>

		<!-- details -->

		<type-field/>

	</fields>

	<collections>

		<children-list
			name="messages"
			type="messageSetMessage"/>

	</collections>

	<event-types>

		<event-type
			name="Messageset message created"
			text="%0 created message %1 in %2 on %3 with number %4, value %5 and message %6"
			admin="yes"/>

		<event-type
			name="Messageset message removed"
			text="%0 removed message %1 from %2"
			admin="yes"/>

		<event-type
			name="Messageset message route"
			text="%0 set route for message %1 in %2 to %3"
			admin="yes"/>

		<event-type
			name="Messageset message number"
			text="%0 set number for message %1 in %2 to %3"
			admin="yes"/>

		<event-type
			name="Messageset message value"
			text="%0 set value for message %1 in %2 to %3"
			admin="yes"/>

		<event-type
			name="Messageset message message"
			text="%0 set message for message %1 in %2 to %3"
			admin="yes"/>

	</event-types>

</record>